baseconvert/ButtonRow.qml
baseconvert/__init__.py
baseconvert/__main__.py
baseconvert/app.qml
baseconvert/baseconvert.py
baseconvert/gui.py
baseconvert-2.0.4.dist-info/LICENSE.txt
baseconvert-2.0.4.dist-info/METADATA
baseconvert-2.0.4.dist-info/WHEEL
baseconvert-2.0.4.dist-info/entry_points.txt
baseconvert-2.0.4.dist-info/top_level.txt
baseconvert-2.0.4.dist-info/RECORD
