Metadata-Version: 2.1
Name: baseconvert
Version: 2.0.4
Summary: Convert numbers between bases.
Home-page: https://github.com/BreadMakesYouFull/baseconvert.git
Author: squdle, BreadMakesYouFull
License: MIT
Keywords: base bases radix numeral system number hex dec bin hexidecimalbinary decimal fraction fractions integer convert gui
Classifier: Programming Language :: Python
Classifier: Programming Language :: Python :: 3
Classifier: Programming Language :: Python :: 3 :: Only
Classifier: Topic :: Education
Classifier: Topic :: Scientific/Engineering :: Mathematics
Classifier: Intended Audience :: Education
Classifier: License :: OSI Approved :: MIT License
License-File: LICENSE.txt
Provides-Extra: gui
Requires-Dist: pyside6 ; extra == 'gui'
